<annotation>
	<folder>JPEGImages</folder>
	<filename>00704.jpg</filename>
	<path>E:\Dataset\MyDataset\桥梁表面损伤\JPEGImages\00704.jpg</path>
	<source>
		<database>Unknown</database>
	</source>
	<size>
		<width>4608</width>
		<height>3456</height>
		<depth>3</depth>
	</size>
	<segmented>0</segmented>
	<object>
		<name>rebar</name>
		<pose>Unspecified</pose>
		<truncated>0</truncated>
		<difficult>0</difficult>
		<bndbox>
			<xmin>27</xmin>
			<ymin>890</ymin>
			<xmax>235</xmax>
			<ymax>1146</ymax>
		</bndbox>
	</object>
	<object>
		<name>rebar</name>
		<pose>Unspecified</pose>
		<truncated>0</truncated>
		<difficult>0</difficult>
		<bndbox>
			<xmin>2516</xmin>
			<ymin>287</ymin>
			<xmax>2683</xmax>
			<ymax>2672</ymax>
		</bndbox>
	</object>
	<object>
		<name>rebar</name>
		<pose>Unspecified</pose>
		<truncated>0</truncated>
		<difficult>0</difficult>
		<bndbox>
			<xmin>4020</xmin>
			<ymin>31</ymin>
			<xmax>4168</xmax>
			<ymax>2213</ymax>
		</bndbox>
	</object>
	<object>
		<name>rebar</name>
		<pose>Unspecified</pose>
		<truncated>0</truncated>
		<difficult>0</difficult>
		<bndbox>
			<xmin>1049</xmin>
			<ymin>1424</ymin>
			<xmax>1170</xmax>
			<ymax>2042</ymax>
		</bndbox>
	</object>
	<object>
		<name>rebar</name>
		<pose>Unspecified</pose>
		<truncated>0</truncated>
		<difficult>0</difficult>
		<bndbox>
			<xmin>1036</xmin>
			<ymin>2379</ymin>
			<xmax>1196</xmax>
			<ymax>3442</ymax>
		</bndbox>
	</object>
	<object>
		<name>separation</name>
		<pose>Unspecified</pose>
		<truncated>0</truncated>
		<difficult>0</difficult>
		<bndbox>
			<xmin>825</xmin>
			<ymin>359</ymin>
			<xmax>1200</xmax>
			<ymax>945</ymax>
		</bndbox>
	</object>
	<object>
		<name>separation</name>
		<pose>Unspecified</pose>
		<truncated>0</truncated>
		<difficult>0</difficult>
		<bndbox>
			<xmin>11</xmin>
			<ymin>490</ymin>
			<xmax>118</xmax>
			<ymax>994</ymax>
		</bndbox>
	</object>
	<object>
		<name>separation</name>
		<pose>Unspecified</pose>
		<truncated>0</truncated>
		<difficult>0</difficult>
		<bndbox>
			<xmin>1125</xmin>
			<ymin>1861</ymin>
			<xmax>1533</xmax>
			<ymax>2957</ymax>
		</bndbox>
	</object>
	<object>
		<name>separation</name>
		<pose>Unspecified</pose>
		<truncated>0</truncated>
		<difficult>0</difficult>
		<bndbox>
			<xmin>1429</xmin>
			<ymin>2635</ymin>
			<xmax>3074</xmax>
			<ymax>3246</ymax>
		</bndbox>
	</object>
	<object>
		<name>separation</name>
		<pose>Unspecified</pose>
		<truncated>1</truncated>
		<difficult>0</difficult>
		<bndbox>
			<xmin>2650</xmin>
			<ymin>1899</ymin>
			<xmax>4608</xmax>
			<ymax>3456</ymax>
		</bndbox>
	</object>
	<object>
		<name>spall</name>
		<pose>Unspecified</pose>
		<truncated>0</truncated>
		<difficult>0</difficult>
		<bndbox>
			<xmin>2203</xmin>
			<ymin>245</ymin>
			<xmax>4259</xmax>
			<ymax>2649</ymax>
		</bndbox>
	</object>
	<object>
		<name>spall</name>
		<pose>Unspecified</pose>
		<truncated>0</truncated>
		<difficult>0</difficult>
		<bndbox>
			<xmin>925</xmin>
			<ymin>1424</ymin>
			<xmax>1466</xmax>
			<ymax>2031</ymax>
		</bndbox>
	</object>
	<object>
		<name>spall</name>
		<pose>Unspecified</pose>
		<truncated>1</truncated>
		<difficult>0</difficult>
		<bndbox>
			<xmin>814</xmin>
			<ymin>2209</ymin>
			<xmax>1285</xmax>
			<ymax>3456</ymax>
		</bndbox>
	</object>
	<object>
		<name>spall</name>
		<pose>Unspecified</pose>
		<truncated>0</truncated>
		<difficult>0</difficult>
		<bndbox>
			<xmin>3777</xmin>
			<ymin>9</ymin>
			<xmax>4544</xmax>
			<ymax>816</ymax>
		</bndbox>
	</object>
</annotation>
